oeis_cli/__init__.py
oeis_cli/__main__.py
oeis_cli/oeis.py
oeis_cli/process.py
oeis_cli/search.py
oeis_cli-0.2.1.dist-info/METADATA
oeis_cli-0.2.1.dist-info/RECORD
oeis_cli-0.2.1.dist-info/WHEEL
oeis_cli-0.2.1.dist-info/entry_points.txt
oeis_cli-0.2.1.dist-info/top_level.txt
