Metadata-Version: 2.1
Name: oeis-cli
Version: 0.2.1
Summary: Command-line interface for OEIS.
Home-page: https://github.com/dfbenjamin/oeis-cli/
Author: Dominic Benjamin
Author-email: domfbenjamin@gmail.com
License: UNKNOWN
Platform: UNKNOWN
Classifier: License :: OSI Approved :: MIT License
Classifier: Operating System :: OS Independent
Classifier: Programming Language :: Python
